{
  "project_info": {
    "project_number": "886802055145",
    "firebase_url": "https://doctors-for-everyone-default-rtdb.firebaseio.com",
    "project_id": "doctors-for-everyone",
    "storage_bucket": "doctors-for-everyone.appspot.com"
  },
  "client": [
    {
      "client_info": {
        "mobilesdk_app_id": "1:886802055145:android:c9fed17adcab556764d578",
        "android_client_info": {
          "package_name": "com.klemer.doctorsforeveryone"
        }
      },
      "oauth_client": [
        {
          "client_id": "886802055145-b1br1slokiuj44d6f8cqlgpkvfp9psqv.apps.googleusercontent.com",
          "client_type": 1,
          "android_info": {
            "package_name": "com.klemer.doctorsforeveryone",
            "certificate_hash": "aac6c6a8d72babaf455290a8618ec1c06132f476"
          }
        },
        {
          "client_id": "886802055145-gblrduviamr9uuofhnrch13qhafg1h91.apps.googleusercontent.com",
          "client_type": 1,
          "android_info": {
            "package_name": "com.klemer.doctorsforeveryone",
            "certificate_hash": "c09f2fb9e10b9f178edcd5535ea0cb28c5de4301"
          }
        },
        {
          "client_id": "886802055145-ov8mfaqmjiilp8c6jtptdh0mciue8c97.apps.googleusercontent.com",
          "client_type": 3
        }
      ],
      "api_key": [
        {
          "current_key": "AIzaSyBn6ixcBvn2U5319HcJ_prXY7sNtzthurY"
        }
      ],
      "services": {
        "appinvite_service": {
          "other_platform_oauth_client": [
            {
              "client_id": "886802055145-ov8mfaqmjiilp8c6jtptdh0mciue8c97.apps.googleusercontent.com",
              "client_type": 3
            }
          ]
        }
      }
    }
  ],
  "configuration_version": "1"
}